takayi/__init__.py
takayi/exc.py
takayi/parser.py
takayi/typing.py
takayi-0.3.3.dist-info/DESCRIPTION.rst
takayi-0.3.3.dist-info/METADATA
takayi-0.3.3.dist-info/RECORD
takayi-0.3.3.dist-info/WHEEL
takayi-0.3.3.dist-info/metadata.json
takayi-0.3.3.dist-info/top_level.txt
tests/__init__.py
tests/test_parser.py
tests/test_typing.py
