Metadata-Version: 2.0
Name: takayi
Version: 0.3.3
Summary: Type hints for python 2.x
Home-page: https://github.com/MrKiven/Takayi
Author: Kiven
Author-email: kiven.mr@gmail.com
License: UNKNOWN
Platform: UNKNOWN
